AnotherLibrary/__init__.py
AnotherLibrary-0.2.dist-info/LICENSE
AnotherLibrary-0.2.dist-info/METADATA
AnotherLibrary-0.2.dist-info/WHEEL
AnotherLibrary-0.2.dist-info/top_level.txt
AnotherLibrary-0.2.dist-info/RECORD
