Metadata-Version: 2.1
Name: AnotherLibrary
Version: 0.2
Summary: This is my library
Home-page: https://github.com/jhlopezm
Author: Jorge Hernán López
Author-email: jhlopezm2@gmail.com
License: UNKNOWN
Project-URL: Bug Tracker, https://github.com/pypa/sampleproject/issues
Platform: UNKNOWN
Classifier: Programming Language :: Python :: 3
Classifier: License :: OSI Approved :: MIT License
Classifier: Operating System :: OS Independent
Requires-Python: >=3.6
